cherami_client/__init__.py
cherami_client/ack_message_result.py
cherami_client/ack_thread.py
cherami_client/client.py
cherami_client/consumer.py
cherami_client/consumer_thread.py
cherami_client/publisher.py
cherami_client/publisher_thread.py
cherami_client/reconfigure_thread.py
cherami_client/idl/cherami.thrift
cherami_client/lib/__init__.py
cherami_client/lib/cherami.py
cherami_client/lib/cherami_frontend.py
cherami_client/lib/cherami_input.py
cherami_client/lib/cherami_output.py
cherami_client/lib/util.py
cherami_client-1.0.3.dist-info/DESCRIPTION.rst
cherami_client-1.0.3.dist-info/METADATA
cherami_client-1.0.3.dist-info/RECORD
cherami_client-1.0.3.dist-info/WHEEL
cherami_client-1.0.3.dist-info/metadata.json
cherami_client-1.0.3.dist-info/top_level.txt
