Metadata-Version: 2.0
Name: cherami-client
Version: 1.0.3
Summary: Cherami Python Client Library
Home-page: https://github.com/uber/cherami-client-python
Author: Wei Han
Author-email: weihan@uber.com
License: MIT
Keywords: cherami python client
Platform: UNKNOWN
Classifier: Development Status :: 5 - Production/Stable
Classifier: Intended Audience :: Developers
Classifier: License :: OSI Approved :: MIT License
Classifier: Natural Language :: English
Classifier: Programming Language :: Python :: 2.7
Requires-Dist: PyYAML
Requires-Dist: clay-flask
Requires-Dist: crcmod
Requires-Dist: tchannel (>=1.0.1)
Requires-Dist: zest.releaser (>=6.0,<7.0)
Provides-Extra: tests
Requires-Dist: coverage (==4.0.3); extra == 'tests'
Requires-Dist: flake8 (==2.5.4); extra == 'tests'
Requires-Dist: funcsigs (==1.0.2); extra == 'tests'
Requires-Dist: mccabe (==0.4.0); extra == 'tests'
Requires-Dist: mock (==2.0.0); extra == 'tests'
Requires-Dist: pbr (==1.9.1); extra == 'tests'
Requires-Dist: pep8 (==1.7.0); extra == 'tests'
Requires-Dist: py (==1.4.31); extra == 'tests'
Requires-Dist: pyflakes (==1.0.0); extra == 'tests'
Requires-Dist: pytest (==2.8.7); extra == 'tests'
Requires-Dist: pytest-cov; extra == 'tests'
Requires-Dist: pytest-ipdb (==0.1-prerelease2); extra == 'tests'
Requires-Dist: pytest-tornado; extra == 'tests'
Requires-Dist: six (==1.10.0); extra == 'tests'
